{
	"entries" : 
	[
		{
			"name" : "ALSoundProcessing_BINARY_DIR",
			"properties" : 
			[
				{
					"name" : "HELPSTRING",
					"value" : "Value Computed by CMake"
				}
			],
			"type" : "STATIC",
			"value" : "/home/yufeng/naoTalk/record/build"
		},
		{
			"name" : "ALSoundProcessing_INTERNAL",
			"properties" : 
			[
				{
					"name" : "HELPSTRING",
					"value" : ""
				}
			],
			"type" : "INTERNAL",
			"value" : "FALSE"
		},
		{
			"name" : "ALSoundProcessing_IS_TOP_LEVEL",
			"properties" : 
			[
				{
					"name" : "HELPSTRING",
					"value" : "Value Computed by CMake"
				}
			],
			"type" : "STATIC",
			"value" : "ON"
		},
		{
			"name" : "ALSoundProcessing_LIB_DEPENDS",
			"properties" : 
			[
				{
					"name" : "HELPSTRING",
					"value" : "Dependencies for the target"
				}
			],
			"type" : "STATIC",
			"value" : "general;msc;general;rt;general;dl;general;pthread;general;asound;general;stdc++;general;/home/yufeng/naoTalk/lib/libalcommon.so;general;/home/yufeng/naoTalk/lib/libalproxies.so;general;/home/yufeng/naoTalk/lib/libalthread.so;general;/home/yufeng/naoTalk/lib/libalvalue.so;general;/home/yufeng/naoTalk/lib/libalerror.so;general;/home/yufeng/naoTalk/lib/libqi.so;general;/home/yufeng/naoTalk/lib/libboost_system.so.1.59.0;general;/home/yufeng/naoTalk/lib/libalaudio.so;general;/home/yufeng/naoTalk/lib/libalextractor.so;"
		},
		{
			"name" : "ALSoundProcessing_NO_INSTALL",
			"properties" : 
			[
				{
					"name" : "HELPSTRING",
					"value" : ""
				}
			],
			"type" : "INTERNAL",
			"value" : "FALSE"
		},
		{
			"name" : "ALSoundProcessing_SOURCE_DIR",
			"properties" : 
			[
				{
					"name" : "HELPSTRING",
					"value" : "Value Computed by CMake"
				}
			],
			"type" : "STATIC",
			"value" : "/home/yufeng/naoTalk/record"
		},
		{
			"name" : "ALSoundProcessing_SUBFOLDER",
			"properties" : 
			[
				{
					"name" : "HELPSTRING",
					"value" : ""
				}
			],
			"type" : "INTERNAL",
			"value" : ""
		},
		{
			"name" : "BUILD_PERF_TESTS",
			"properties" : 
			[
				{
					"name" : "HELPSTRING",
					"value" : ""
				}
			],
			"type" : "INTERNAL",
			"value" : "OFF"
		},
		{
			"name" : "BUILD_TESTS",
			"properties" : 
			[
				{
					"name" : "HELPSTRING",
					"value" : ""
				}
			],
			"type" : "INTERNAL",
			"value" : "ON"
		},
		{
			"name" : "CMAKE_ADDR2LINE",
			"properties" : 
			[
				{
					"name" : "ADVANCED",
					"value" : "1"
				},
				{
					"name" : "HELPSTRING",
					"value" : "Path to a program."
				}
			],
			"type" : "FILEPATH",
			"value" : "/usr/bin/addr2line"
		},
		{
			"name" : "CMAKE_AR",
			"properties" : 
			[
				{
					"name" : "ADVANCED",
					"value" : "1"
				},
				{
					"name" : "HELPSTRING",
					"value" : "Path to a program."
				}
			],
			"type" : "FILEPATH",
			"value" : "/usr/bin/ar"
		},
		{
			"name" : "CMAKE_BUILD_TYPE",
			"properties" : 
			[
				{
					"name" : "HELPSTRING",
					"value" : "No help, variable specified on the command line."
				}
			],
			"type" : "STRING",
			"value" : "Debug"
		},
		{
			"name" : "CMAKE_CACHEFILE_DIR",
			"properties" : 
			[
				{
					"name" : "HELPSTRING",
					"value" : "This is the directory where this CMakeCache.txt was created"
				}
			],
			"type" : "INTERNAL",
			"value" : "/home/yufeng/naoTalk/record/build"
		},
		{
			"name" : "CMAKE_CACHE_MAJOR_VERSION",
			"properties" : 
			[
				{
					"name" : "HELPSTRING",
					"value" : "Major version of cmake used to create the current loaded cache"
				}
			],
			"type" : "INTERNAL",
			"value" : "3"
		},
		{
			"name" : "CMAKE_CACHE_MINOR_VERSION",
			"properties" : 
			[
				{
					"name" : "HELPSTRING",
					"value" : "Minor version of cmake used to create the current loaded cache"
				}
			],
			"type" : "INTERNAL",
			"value" : "22"
		},
		{
			"name" : "CMAKE_CACHE_PATCH_VERSION",
			"properties" : 
			[
				{
					"name" : "HELPSTRING",
					"value" : "Patch version of cmake used to create the current loaded cache"
				}
			],
			"type" : "INTERNAL",
			"value" : "1"
		},
		{
			"name" : "CMAKE_COLOR_MAKEFILE",
			"properties" : 
			[
				{
					"name" : "ADVANCED",
					"value" : "1"
				},
				{
					"name" : "HELPSTRING",
					"value" : "Enable/Disable color output during build."
				}
			],
			"type" : "BOOL",
			"value" : "ON"
		},
		{
			"name" : "CMAKE_COMMAND",
			"properties" : 
			[
				{
					"name" : "HELPSTRING",
					"value" : "Path to CMake executable."
				}
			],
			"type" : "INTERNAL",
			"value" : "/usr/bin/cmake"
		},
		{
			"name" : "CMAKE_CPACK_COMMAND",
			"properties" : 
			[
				{
					"name" : "HELPSTRING",
					"value" : "Path to cpack program executable."
				}
			],
			"type" : "INTERNAL",
			"value" : "/usr/bin/cpack"
		},
		{
			"name" : "CMAKE_CTEST_COMMAND",
			"properties" : 
			[
				{
					"name" : "HELPSTRING",
					"value" : "Path to ctest program executable."
				}
			],
			"type" : "INTERNAL",
			"value" : "/usr/bin/ctest"
		},
		{
			"name" : "CMAKE_CXX_COMPILER",
			"properties" : 
			[
				{
					"name" : "ADVANCED",
					"value" : "1"
				},
				{
					"name" : "HELPSTRING",
					"value" : "No help, variable specified on the command line."
				}
			],
			"type" : "FILEPATH",
			"value" : "/usr/bin/g++"
		},
		{
			"name" : "CMAKE_CXX_COMPILER_AR",
			"properties" : 
			[
				{
					"name" : "ADVANCED",
					"value" : "1"
				},
				{
					"name" : "HELPSTRING",
					"value" : "A wrapper around 'ar' adding the appropriate '--plugin' option for the GCC compiler"
				}
			],
			"type" : "FILEPATH",
			"value" : "/usr/bin/gcc-ar-11"
		},
		{
			"name" : "CMAKE_CXX_COMPILER_RANLIB",
			"properties" : 
			[
				{
					"name" : "ADVANCED",
					"value" : "1"
				},
				{
					"name" : "HELPSTRING",
					"value" : "A wrapper around 'ranlib' adding the appropriate '--plugin' option for the GCC compiler"
				}
			],
			"type" : "FILEPATH",
			"value" : "/usr/bin/gcc-ranlib-11"
		},
		{
			"name" : "CMAKE_CXX_FLAGS",
			"properties" : 
			[
				{
					"name" : "ADVANCED",
					"value" : "1"
				},
				{
					"name" : "HELPSTRING",
					"value" : "Flags used by the CXX compiler during all build types."
				}
			],
			"type" : "STRING",
			"value" : ""
		},
		{
			"name" : "CMAKE_CXX_FLAGS_DEBUG",
			"properties" : 
			[
				{
					"name" : "ADVANCED",
					"value" : "1"
				},
				{
					"name" : "HELPSTRING",
					"value" : "Flags used by the CXX compiler during DEBUG builds."
				}
			],
			"type" : "STRING",
			"value" : "-g"
		},
		{
			"name" : "CMAKE_CXX_FLAGS_MINSIZEREL",
			"properties" : 
			[
				{
					"name" : "ADVANCED",
					"value" : "1"
				},
				{
					"name" : "HELPSTRING",
					"value" : "Flags used by the CXX compiler during MINSIZEREL builds."
				}
			],
			"type" : "STRING",
			"value" : "-Os -DNDEBUG"
		},
		{
			"name" : "CMAKE_CXX_FLAGS_RELEASE",
			"properties" : 
			[
				{
					"name" : "ADVANCED",
					"value" : "1"
				},
				{
					"name" : "HELPSTRING",
					"value" : "Flags used by the CXX compiler during RELEASE builds."
				}
			],
			"type" : "STRING",
			"value" : "-O3 -DNDEBUG"
		},
		{
			"name" : "CMAKE_CXX_FLAGS_RELWITHDEBINFO",
			"properties" : 
			[
				{
					"name" : "ADVANCED",
					"value" : "1"
				},
				{
					"name" : "HELPSTRING",
					"value" : "Flags used by the CXX compiler during RELWITHDEBINFO builds."
				}
			],
			"type" : "STRING",
			"value" : "-O2 -g -DNDEBUG"
		},
		{
			"name" : "CMAKE_C_COMPILER",
			"properties" : 
			[
				{
					"name" : "ADVANCED",
					"value" : "1"
				},
				{
					"name" : "HELPSTRING",
					"value" : "No help, variable specified on the command line."
				}
			],
			"type" : "FILEPATH",
			"value" : "/usr/bin/gcc"
		},
		{
			"name" : "CMAKE_C_COMPILER_AR",
			"properties" : 
			[
				{
					"name" : "ADVANCED",
					"value" : "1"
				},
				{
					"name" : "HELPSTRING",
					"value" : "A wrapper around 'ar' adding the appropriate '--plugin' option for the GCC compiler"
				}
			],
			"type" : "FILEPATH",
			"value" : "/usr/bin/gcc-ar-11"
		},
		{
			"name" : "CMAKE_C_COMPILER_RANLIB",
			"properties" : 
			[
				{
					"name" : "ADVANCED",
					"value" : "1"
				},
				{
					"name" : "HELPSTRING",
					"value" : "A wrapper around 'ranlib' adding the appropriate '--plugin' option for the GCC compiler"
				}
			],
			"type" : "FILEPATH",
			"value" : "/usr/bin/gcc-ranlib-11"
		},
		{
			"name" : "CMAKE_C_FLAGS",
			"properties" : 
			[
				{
					"name" : "ADVANCED",
					"value" : "1"
				},
				{
					"name" : "HELPSTRING",
					"value" : "Flags used by the C compiler during all build types."
				}
			],
			"type" : "STRING",
			"value" : ""
		},
		{
			"name" : "CMAKE_C_FLAGS_DEBUG",
			"properties" : 
			[
				{
					"name" : "ADVANCED",
					"value" : "1"
				},
				{
					"name" : "HELPSTRING",
					"value" : "Flags used by the C compiler during DEBUG builds."
				}
			],
			"type" : "STRING",
			"value" : "-g"
		},
		{
			"name" : "CMAKE_C_FLAGS_MINSIZEREL",
			"properties" : 
			[
				{
					"name" : "ADVANCED",
					"value" : "1"
				},
				{
					"name" : "HELPSTRING",
					"value" : "Flags used by the C compiler during MINSIZEREL builds."
				}
			],
			"type" : "STRING",
			"value" : "-Os -DNDEBUG"
		},
		{
			"name" : "CMAKE_C_FLAGS_RELEASE",
			"properties" : 
			[
				{
					"name" : "ADVANCED",
					"value" : "1"
				},
				{
					"name" : "HELPSTRING",
					"value" : "Flags used by the C compiler during RELEASE builds."
				}
			],
			"type" : "STRING",
			"value" : "-O3 -DNDEBUG"
		},
		{
			"name" : "CMAKE_C_FLAGS_RELWITHDEBINFO",
			"properties" : 
			[
				{
					"name" : "ADVANCED",
					"value" : "1"
				},
				{
					"name" : "HELPSTRING",
					"value" : "Flags used by the C compiler during RELWITHDEBINFO builds."
				}
			],
			"type" : "STRING",
			"value" : "-O2 -g -DNDEBUG"
		},
		{
			"name" : "CMAKE_DLLTOOL",
			"properties" : 
			[
				{
					"name" : "ADVANCED",
					"value" : "1"
				},
				{
					"name" : "HELPSTRING",
					"value" : "Path to a program."
				}
			],
			"type" : "FILEPATH",
			"value" : "CMAKE_DLLTOOL-NOTFOUND"
		},
		{
			"name" : "CMAKE_EXECUTABLE_FORMAT",
			"properties" : 
			[
				{
					"name" : "HELPSTRING",
					"value" : "Executable file format"
				}
			],
			"type" : "INTERNAL",
			"value" : "ELF"
		},
		{
			"name" : "CMAKE_EXE_LINKER_FLAGS",
			"properties" : 
			[
				{
					"name" : "ADVANCED",
					"value" : "1"
				},
				{
					"name" : "HELPSTRING",
					"value" : "Flags used by the linker during all build types."
				}
			],
			"type" : "STRING",
			"value" : ""
		},
		{
			"name" : "CMAKE_EXE_LINKER_FLAGS_DEBUG",
			"properties" : 
			[
				{
					"name" : "ADVANCED",
					"value" : "1"
				},
				{
					"name" : "HELPSTRING",
					"value" : "Flags used by the linker during DEBUG builds."
				}
			],
			"type" : "STRING",
			"value" : ""
		},
		{
			"name" : "CMAKE_EXE_LINKER_FLAGS_MINSIZEREL",
			"properties" : 
			[
				{
					"name" : "ADVANCED",
					"value" : "1"
				},
				{
					"name" : "HELPSTRING",
					"value" : "Flags used by the linker during MINSIZEREL builds."
				}
			],
			"type" : "STRING",
			"value" : ""
		},
		{
			"name" : "CMAKE_EXE_LINKER_FLAGS_RELEASE",
			"properties" : 
			[
				{
					"name" : "ADVANCED",
					"value" : "1"
				},
				{
					"name" : "HELPSTRING",
					"value" : "Flags used by the linker during RELEASE builds."
				}
			],
			"type" : "STRING",
			"value" : ""
		},
		{
			"name" : "CMAKE_EXE_LINKER_FLAGS_RELWITHDEBINFO",
			"properties" : 
			[
				{
					"name" : "ADVANCED",
					"value" : "1"
				},
				{
					"name" : "HELPSTRING",
					"value" : "Flags used by the linker during RELWITHDEBINFO builds."
				}
			],
			"type" : "STRING",
			"value" : ""
		},
		{
			"name" : "CMAKE_EXPORT_COMPILE_COMMANDS",
			"properties" : 
			[
				{
					"name" : "HELPSTRING",
					"value" : "No help, variable specified on the command line."
				}
			],
			"type" : "BOOL",
			"value" : "TRUE"
		},
		{
			"name" : "CMAKE_EXTRA_GENERATOR",
			"properties" : 
			[
				{
					"name" : "HELPSTRING",
					"value" : "Name of external makefile project generator."
				}
			],
			"type" : "INTERNAL",
			"value" : ""
		},
		{
			"name" : "CMAKE_GENERATOR",
			"properties" : 
			[
				{
					"name" : "HELPSTRING",
					"value" : "Name of generator."
				}
			],
			"type" : "INTERNAL",
			"value" : "Unix Makefiles"
		},
		{
			"name" : "CMAKE_GENERATOR_INSTANCE",
			"properties" : 
			[
				{
					"name" : "HELPSTRING",
					"value" : "Generator instance identifier."
				}
			],
			"type" : "INTERNAL",
			"value" : ""
		},
		{
			"name" : "CMAKE_GENERATOR_PLATFORM",
			"properties" : 
			[
				{
					"name" : "HELPSTRING",
					"value" : "Name of generator platform."
				}
			],
			"type" : "INTERNAL",
			"value" : ""
		},
		{
			"name" : "CMAKE_GENERATOR_TOOLSET",
			"properties" : 
			[
				{
					"name" : "HELPSTRING",
					"value" : "Name of generator toolset."
				}
			],
			"type" : "INTERNAL",
			"value" : ""
		},
		{
			"name" : "CMAKE_HOME_DIRECTORY",
			"properties" : 
			[
				{
					"name" : "HELPSTRING",
					"value" : "Source directory with the top level CMakeLists.txt file for this project"
				}
			],
			"type" : "INTERNAL",
			"value" : "/home/yufeng/naoTalk/record"
		},
		{
			"name" : "CMAKE_INSTALL_PREFIX",
			"properties" : 
			[
				{
					"name" : "HELPSTRING",
					"value" : ""
				}
			],
			"type" : "INTERNAL",
			"value" : "/"
		},
		{
			"name" : "CMAKE_INSTALL_SO_NO_EXE",
			"properties" : 
			[
				{
					"name" : "HELPSTRING",
					"value" : "Install .so files without execute permission."
				}
			],
			"type" : "INTERNAL",
			"value" : "1"
		},
		{
			"name" : "CMAKE_LINKER",
			"properties" : 
			[
				{
					"name" : "ADVANCED",
					"value" : "1"
				},
				{
					"name" : "HELPSTRING",
					"value" : "Path to a program."
				}
			],
			"type" : "FILEPATH",
			"value" : "/usr/bin/ld"
		},
		{
			"name" : "CMAKE_MAKE_PROGRAM",
			"properties" : 
			[
				{
					"name" : "ADVANCED",
					"value" : "1"
				},
				{
					"name" : "HELPSTRING",
					"value" : "Path to a program."
				}
			],
			"type" : "FILEPATH",
			"value" : "/usr/bin/gmake"
		},
		{
			"name" : "CMAKE_MODULE_LINKER_FLAGS",
			"properties" : 
			[
				{
					"name" : "ADVANCED",
					"value" : "1"
				},
				{
					"name" : "HELPSTRING",
					"value" : "Flags used by the linker during the creation of modules during all build types."
				}
			],
			"type" : "STRING",
			"value" : ""
		},
		{
			"name" : "CMAKE_MODULE_LINKER_FLAGS_DEBUG",
			"properties" : 
			[
				{
					"name" : "ADVANCED",
					"value" : "1"
				},
				{
					"name" : "HELPSTRING",
					"value" : "Flags used by the linker during the creation of modules during DEBUG builds."
				}
			],
			"type" : "STRING",
			"value" : ""
		},
		{
			"name" : "CMAKE_MODULE_LINKER_FLAGS_MINSIZEREL",
			"properties" : 
			[
				{
					"name" : "ADVANCED",
					"value" : "1"
				},
				{
					"name" : "HELPSTRING",
					"value" : "Flags used by the linker during the creation of modules during MINSIZEREL builds."
				}
			],
			"type" : "STRING",
			"value" : ""
		},
		{
			"name" : "CMAKE_MODULE_LINKER_FLAGS_RELEASE",
			"properties" : 
			[
				{
					"name" : "ADVANCED",
					"value" : "1"
				},
				{
					"name" : "HELPSTRING",
					"value" : "Flags used by the linker during the creation of modules during RELEASE builds."
				}
			],
			"type" : "STRING",
			"value" : ""
		},
		{
			"name" : "CMAKE_MODULE_LINKER_FLAGS_RELWITHDEBINFO",
			"properties" : 
			[
				{
					"name" : "ADVANCED",
					"value" : "1"
				},
				{
					"name" : "HELPSTRING",
					"value" : "Flags used by the linker during the creation of modules during RELWITHDEBINFO builds."
				}
			],
			"type" : "STRING",
			"value" : ""
		},
		{
			"name" : "CMAKE_MODULE_PATH",
			"properties" : 
			[
				{
					"name" : "HELPSTRING",
					"value" : ""
				}
			],
			"type" : "INTERNAL",
			"value" : "/home/yufeng/.local/share/cmake/qibuild/.."
		},
		{
			"name" : "CMAKE_NM",
			"properties" : 
			[
				{
					"name" : "ADVANCED",
					"value" : "1"
				},
				{
					"name" : "HELPSTRING",
					"value" : "Path to a program."
				}
			],
			"type" : "FILEPATH",
			"value" : "/usr/bin/nm"
		},
		{
			"name" : "CMAKE_NUMBER_OF_MAKEFILES",
			"properties" : 
			[
				{
					"name" : "HELPSTRING",
					"value" : "number of local generators"
				}
			],
			"type" : "INTERNAL",
			"value" : "1"
		},
		{
			"name" : "CMAKE_OBJCOPY",
			"properties" : 
			[
				{
					"name" : "ADVANCED",
					"value" : "1"
				},
				{
					"name" : "HELPSTRING",
					"value" : "Path to a program."
				}
			],
			"type" : "FILEPATH",
			"value" : "/usr/bin/objcopy"
		},
		{
			"name" : "CMAKE_OBJDUMP",
			"properties" : 
			[
				{
					"name" : "ADVANCED",
					"value" : "1"
				},
				{
					"name" : "HELPSTRING",
					"value" : "Path to a program."
				}
			],
			"type" : "FILEPATH",
			"value" : "/usr/bin/objdump"
		},
		{
			"name" : "CMAKE_PLATFORM_INFO_INITIALIZED",
			"properties" : 
			[
				{
					"name" : "HELPSTRING",
					"value" : "Platform information initialized"
				}
			],
			"type" : "INTERNAL",
			"value" : "1"
		},
		{
			"name" : "CMAKE_PREFIX_PATH",
			"properties" : 
			[
				{
					"name" : "HELPSTRING",
					"value" : ""
				}
			],
			"type" : "INTERNAL",
			"value" : "/home/yufeng/naoTalk/record/build/sdk;/home/yufeng/.local/share/cmake/qibuild/modules/"
		},
		{
			"name" : "CMAKE_PROJECT_DESCRIPTION",
			"properties" : 
			[
				{
					"name" : "HELPSTRING",
					"value" : "Value Computed by CMake"
				}
			],
			"type" : "STATIC",
			"value" : ""
		},
		{
			"name" : "CMAKE_PROJECT_HOMEPAGE_URL",
			"properties" : 
			[
				{
					"name" : "HELPSTRING",
					"value" : "Value Computed by CMake"
				}
			],
			"type" : "STATIC",
			"value" : ""
		},
		{
			"name" : "CMAKE_PROJECT_NAME",
			"properties" : 
			[
				{
					"name" : "HELPSTRING",
					"value" : "Value Computed by CMake"
				}
			],
			"type" : "STATIC",
			"value" : "ALSoundProcessing"
		},
		{
			"name" : "CMAKE_RANLIB",
			"properties" : 
			[
				{
					"name" : "ADVANCED",
					"value" : "1"
				},
				{
					"name" : "HELPSTRING",
					"value" : "Path to a program."
				}
			],
			"type" : "FILEPATH",
			"value" : "/usr/bin/ranlib"
		},
		{
			"name" : "CMAKE_READELF",
			"properties" : 
			[
				{
					"name" : "ADVANCED",
					"value" : "1"
				},
				{
					"name" : "HELPSTRING",
					"value" : "Path to a program."
				}
			],
			"type" : "FILEPATH",
			"value" : "/usr/bin/readelf"
		},
		{
			"name" : "CMAKE_ROOT",
			"properties" : 
			[
				{
					"name" : "HELPSTRING",
					"value" : "Path to CMake installation."
				}
			],
			"type" : "INTERNAL",
			"value" : "/usr/share/cmake-3.22"
		},
		{
			"name" : "CMAKE_SHARED_LINKER_FLAGS",
			"properties" : 
			[
				{
					"name" : "ADVANCED",
					"value" : "1"
				},
				{
					"name" : "HELPSTRING",
					"value" : "Flags used by the linker during the creation of shared libraries during all build types."
				}
			],
			"type" : "STRING",
			"value" : ""
		},
		{
			"name" : "CMAKE_SHARED_LINKER_FLAGS_DEBUG",
			"properties" : 
			[
				{
					"name" : "ADVANCED",
					"value" : "1"
				},
				{
					"name" : "HELPSTRING",
					"value" : "Flags used by the linker during the creation of shared libraries during DEBUG builds."
				}
			],
			"type" : "STRING",
			"value" : ""
		},
		{
			"name" : "CMAKE_SHARED_LINKER_FLAGS_MINSIZEREL",
			"properties" : 
			[
				{
					"name" : "ADVANCED",
					"value" : "1"
				},
				{
					"name" : "HELPSTRING",
					"value" : "Flags used by the linker during the creation of shared libraries during MINSIZEREL builds."
				}
			],
			"type" : "STRING",
			"value" : ""
		},
		{
			"name" : "CMAKE_SHARED_LINKER_FLAGS_RELEASE",
			"properties" : 
			[
				{
					"name" : "ADVANCED",
					"value" : "1"
				},
				{
					"name" : "HELPSTRING",
					"value" : "Flags used by the linker during the creation of shared libraries during RELEASE builds."
				}
			],
			"type" : "STRING",
			"value" : ""
		},
		{
			"name" : "CMAKE_SHARED_LINKER_FLAGS_RELWITHDEBINFO",
			"properties" : 
			[
				{
					"name" : "ADVANCED",
					"value" : "1"
				},
				{
					"name" : "HELPSTRING",
					"value" : "Flags used by the linker during the creation of shared libraries during RELWITHDEBINFO builds."
				}
			],
			"type" : "STRING",
			"value" : ""
		},
		{
			"name" : "CMAKE_SKIP_INSTALL_RPATH",
			"properties" : 
			[
				{
					"name" : "ADVANCED",
					"value" : "1"
				},
				{
					"name" : "HELPSTRING",
					"value" : "If set, runtime paths are not added when installing shared libraries, but are added when building."
				}
			],
			"type" : "BOOL",
			"value" : "NO"
		},
		{
			"name" : "CMAKE_SKIP_RPATH",
			"properties" : 
			[
				{
					"name" : "ADVANCED",
					"value" : "1"
				},
				{
					"name" : "HELPSTRING",
					"value" : "If set, runtime paths are not added when using shared libraries."
				}
			],
			"type" : "BOOL",
			"value" : "NO"
		},
		{
			"name" : "CMAKE_STATIC_LINKER_FLAGS",
			"properties" : 
			[
				{
					"name" : "ADVANCED",
					"value" : "1"
				},
				{
					"name" : "HELPSTRING",
					"value" : "Flags used by the linker during the creation of static libraries during all build types."
				}
			],
			"type" : "STRING",
			"value" : ""
		},
		{
			"name" : "CMAKE_STATIC_LINKER_FLAGS_DEBUG",
			"properties" : 
			[
				{
					"name" : "ADVANCED",
					"value" : "1"
				},
				{
					"name" : "HELPSTRING",
					"value" : "Flags used by the linker during the creation of static libraries during DEBUG builds."
				}
			],
			"type" : "STRING",
			"value" : ""
		},
		{
			"name" : "CMAKE_STATIC_LINKER_FLAGS_MINSIZEREL",
			"properties" : 
			[
				{
					"name" : "ADVANCED",
					"value" : "1"
				},
				{
					"name" : "HELPSTRING",
					"value" : "Flags used by the linker during the creation of static libraries during MINSIZEREL builds."
				}
			],
			"type" : "STRING",
			"value" : ""
		},
		{
			"name" : "CMAKE_STATIC_LINKER_FLAGS_RELEASE",
			"properties" : 
			[
				{
					"name" : "ADVANCED",
					"value" : "1"
				},
				{
					"name" : "HELPSTRING",
					"value" : "Flags used by the linker during the creation of static libraries during RELEASE builds."
				}
			],
			"type" : "STRING",
			"value" : ""
		},
		{
			"name" : "CMAKE_STATIC_LINKER_FLAGS_RELWITHDEBINFO",
			"properties" : 
			[
				{
					"name" : "ADVANCED",
					"value" : "1"
				},
				{
					"name" : "HELPSTRING",
					"value" : "Flags used by the linker during the creation of static libraries during RELWITHDEBINFO builds."
				}
			],
			"type" : "STRING",
			"value" : ""
		},
		{
			"name" : "CMAKE_STRIP",
			"properties" : 
			[
				{
					"name" : "ADVANCED",
					"value" : "1"
				},
				{
					"name" : "HELPSTRING",
					"value" : "Path to a program."
				}
			],
			"type" : "FILEPATH",
			"value" : "/usr/bin/strip"
		},
		{
			"name" : "CMAKE_UNAME",
			"properties" : 
			[
				{
					"name" : "HELPSTRING",
					"value" : "uname command"
				}
			],
			"type" : "INTERNAL",
			"value" : "/usr/bin/uname"
		},
		{
			"name" : "CMAKE_VERBOSE_MAKEFILE",
			"properties" : 
			[
				{
					"name" : "ADVANCED",
					"value" : "1"
				},
				{
					"name" : "HELPSTRING",
					"value" : "If this value is on, makefiles will be generated without the .SILENT directive, and all commands will be echoed to the console during the make.  This is useful for debugging only. With Visual Studio IDE projects all commands are done without /nologo."
				}
			],
			"type" : "BOOL",
			"value" : "FALSE"
		},
		{
			"name" : "PYTHON2_EXECUTABLE",
			"properties" : 
			[
				{
					"name" : "HELPSTRING",
					"value" : "Path to a program."
				}
			],
			"type" : "FILEPATH",
			"value" : "/usr/bin/python2"
		},
		{
			"name" : "QIBUILD_VERSION",
			"properties" : 
			[
				{
					"name" : "HELPSTRING",
					"value" : "qibuild version"
				}
			],
			"type" : "STRING",
			"value" : "3.18"
		},
		{
			"name" : "QI_FORCE_32_BITS",
			"properties" : 
			[
				{
					"name" : "HELPSTRING",
					"value" : "Force 32bits build even when on 64bits"
				}
			],
			"type" : "BOOL",
			"value" : "OFF"
		},
		{
			"name" : "QI_NIGHTLY_TESTS",
			"properties" : 
			[
				{
					"name" : "HELPSTRING",
					"value" : ""
				}
			],
			"type" : "INTERNAL",
			"value" : "OFF"
		},
		{
			"name" : "QI_SDK_BIN",
			"properties" : 
			[
				{
					"name" : "ADVANCED",
					"value" : "1"
				},
				{
					"name" : "HELPSTRING",
					"value" : ""
				}
			],
			"type" : "INTERNAL",
			"value" : "bin"
		},
		{
			"name" : "QI_SDK_CMAKE",
			"properties" : 
			[
				{
					"name" : "ADVANCED",
					"value" : "1"
				},
				{
					"name" : "HELPSTRING",
					"value" : ""
				}
			],
			"type" : "INTERNAL",
			"value" : "share/cmake"
		},
		{
			"name" : "QI_SDK_CMAKE_MODULES",
			"properties" : 
			[
				{
					"name" : "ADVANCED",
					"value" : "1"
				},
				{
					"name" : "HELPSTRING",
					"value" : ""
				}
			],
			"type" : "INTERNAL",
			"value" : "cmake"
		},
		{
			"name" : "QI_SDK_CONF",
			"properties" : 
			[
				{
					"name" : "ADVANCED",
					"value" : "1"
				},
				{
					"name" : "HELPSTRING",
					"value" : ""
				}
			],
			"type" : "INTERNAL",
			"value" : "etc"
		},
		{
			"name" : "QI_SDK_DIR",
			"properties" : 
			[
				{
					"name" : "HELPSTRING",
					"value" : ""
				}
			],
			"type" : "INTERNAL",
			"value" : "/home/yufeng/naoTalk/record/build/sdk"
		},
		{
			"name" : "QI_SDK_DOC",
			"properties" : 
			[
				{
					"name" : "ADVANCED",
					"value" : "1"
				},
				{
					"name" : "HELPSTRING",
					"value" : ""
				}
			],
			"type" : "INTERNAL",
			"value" : "share/doc"
		},
		{
			"name" : "QI_SDK_FRAMEWORK",
			"properties" : 
			[
				{
					"name" : "HELPSTRING",
					"value" : ""
				}
			],
			"type" : "INTERNAL",
			"value" : "Frameworks"
		},
		{
			"name" : "QI_SDK_INCLUDE",
			"properties" : 
			[
				{
					"name" : "ADVANCED",
					"value" : "1"
				},
				{
					"name" : "HELPSTRING",
					"value" : ""
				}
			],
			"type" : "INTERNAL",
			"value" : "include"
		},
		{
			"name" : "QI_SDK_LIB",
			"properties" : 
			[
				{
					"name" : "ADVANCED",
					"value" : "1"
				},
				{
					"name" : "HELPSTRING",
					"value" : ""
				}
			],
			"type" : "INTERNAL",
			"value" : "lib"
		},
		{
			"name" : "QI_SDK_SHARE",
			"properties" : 
			[
				{
					"name" : "ADVANCED",
					"value" : "1"
				},
				{
					"name" : "HELPSTRING",
					"value" : ""
				}
			],
			"type" : "INTERNAL",
			"value" : "share"
		},
		{
			"name" : "QI_VIRTUALENV_PATH",
			"properties" : 
			[
				{
					"name" : "HELPSTRING",
					"value" : ""
				}
			],
			"type" : "INTERNAL",
			"value" : ""
		},
		{
			"name" : "QI_WITH_COVERAGE",
			"properties" : 
			[
				{
					"name" : "HELPSTRING",
					"value" : "Enable code coverage"
				}
			],
			"type" : "BOOL",
			"value" : "OFF"
		},
		{
			"name" : "QI_WITH_DEBUG_INFO",
			"properties" : 
			[
				{
					"name" : "HELPSTRING",
					"value" : "Default is to follow CMAKE_BUILD_TYPE"
				}
			],
			"type" : "BOOL",
			"value" : "ON"
		},
		{
			"name" : "QI_WITH_HARDENING",
			"properties" : 
			[
				{
					"name" : "HELPSTRING",
					"value" : "Enable code hardening flags"
				}
			],
			"type" : "BOOL",
			"value" : "OFF"
		},
		{
			"name" : "QI_WITH_NIGHTLY_TESTS",
			"properties" : 
			[
				{
					"name" : "HELPSTRING",
					"value" : "triggers building of nightly tests"
				}
			],
			"type" : "BOOL",
			"value" : "OFF"
		},
		{
			"name" : "QI_WITH_PERF_TESTS",
			"properties" : 
			[
				{
					"name" : "HELPSTRING",
					"value" : "Triggers building of perf tests"
				}
			],
			"type" : "BOOL",
			"value" : "OFF"
		},
		{
			"name" : "QI_WITH_TESTS",
			"properties" : 
			[
				{
					"name" : "HELPSTRING",
					"value" : "If OFF, no test will be built, and `qibuild test` won't run any test"
				}
			],
			"type" : "BOOL",
			"value" : "ON"
		},
		{
			"name" : "SOUNDPROCESSING_IS_REMOTE",
			"properties" : 
			[
				{
					"name" : "HELPSTRING",
					"value" : "module is compiled as a remote module (ON or OFF)"
				}
			],
			"type" : "BOOL",
			"value" : "ON"
		},
		{
			"name" : "_dpkg_architecture",
			"properties" : 
			[
				{
					"name" : "HELPSTRING",
					"value" : ""
				}
			],
			"type" : "INTERNAL",
			"value" : "/usr/bin/dpkg-architecture"
		},
		{
			"name" : "qibuild_DIR",
			"properties" : 
			[
				{
					"name" : "HELPSTRING",
					"value" : ""
				}
			],
			"type" : "INTERNAL",
			"value" : "/home/yufeng/.local/share/cmake/qibuild"
		}
	],
	"kind" : "cache",
	"version" : 
	{
		"major" : 2,
		"minor" : 0
	}
}
